ezside/__init__.py
ezside/app/__init__.py
ezside/app/_abstract_menu.py
ezside/app/_app.py
ezside/app/_base_window.py
ezside/app/_context_menu.py
ezside/app/_debug_menu.py
ezside/app/_edit_menu.py
ezside/app/_ez_action.py
ezside/app/_file_menu.py
ezside/app/_help_menu.py
ezside/app/_layout_window.py
ezside/app/_main_window.py
ezside/app/_menu_bar.py
ezside/app/_menu_window.py
ezside/app/_status_bar.py
ezside/app/icons/__init__.py
ezside/app/icons/about_conda.png
ezside/app/icons/about_pyside6.png
ezside/app/icons/about_python.png
ezside/app/icons/about_qt.png
ezside/app/icons/add.png
ezside/app/icons/copy.png
ezside/app/icons/cut.png
ezside/app/icons/debug.png
ezside/app/icons/edit_menu.png
ezside/app/icons/exit.png
ezside/app/icons/ferrari_strategy.png
ezside/app/icons/files.png
ezside/app/icons/files_menu.png
ezside/app/icons/help.png
ezside/app/icons/help_menu.png
ezside/app/icons/locked.png
ezside/app/icons/microphone.png
ezside/app/icons/minescript.png
ezside/app/icons/new.png
ezside/app/icons/open.png
ezside/app/icons/paste.png
ezside/app/icons/pogchamp.png
ezside/app/icons/preferences.png
ezside/app/icons/redo.png
ezside/app/icons/risitas.png
ezside/app/icons/save.png
ezside/app/icons/save_as.png
ezside/app/icons/screen_shot.png
ezside/app/icons/select_all.png
ezside/app/icons/undo.png
ezside/app/icons/unlocked.png
ezside/app/icons/workside.png
ezside/basewidgets/__init__.py
ezside/basewidgets/_box_widget.py
ezside/basewidgets/_button_state.py
ezside/basewidgets/_button_style.py
ezside/basewidgets/_label.py
ezside/basewidgets/_push_button.py
ezside/basewidgets/_seven_seg.py
ezside/basewidgets/button_style.json
ezside/dialogs/_OLD_new_dialog.py
ezside/dialogs/__init__.py
ezside/dialogs/_about_python.py
ezside/dialogs/_new_dialog.py
ezside/dialogs/_open_file.py
ezside/dialogs/_save_file.py
ezside/dialogs/_select_dir.py
ezside/layouts/__init__.py
ezside/layouts/_abstract_layout.py
ezside/layouts/_horizontal_layout.py
ezside/layouts/_layout_index.py
ezside-0.1.53.dist-info/LICENSE
ezside-0.1.53.dist-info/METADATA
ezside-0.1.53.dist-info/WHEEL
ezside-0.1.53.dist-info/top_level.txt
ezside-0.1.53.dist-info/RECORD
