Metadata-Version: 2.1
Name: ezside
Version: 0.1.53
Summary: ezside provides examples and utilities for PySide6.
Home-page: https://github.com/AsgerJon/ezside
Author: Asger Jon Vistisen
Author-email: Asger Jon Vistisen <asgerjon2@gmail.com>
Project-URL: Homepage, https://github.com/AsgerJon/ezside
Project-URL: Bug Tracker, https://github.com/AsgerJon/ezside
Classifier: Programming Language :: Python :: 3
Classifier: License :: OSI Approved :: GNU Affero General Public License v3 or later (AGPLv3+)
Classifier: Operating System :: OS Independent
Requires-Python: >=3.9
License-File: LICENSE
